setup.py
hypercouch/__init__.py
hypercouch/index.py
hypercouch.egg-info/PKG-INFO
hypercouch.egg-info/SOURCES.txt
hypercouch.egg-info/dependency_links.txt
hypercouch.egg-info/requires.txt
hypercouch.egg-info/top_level.txt
hypercouch.egg-info/zip-safe
tests/__init__.py
tests/attr_test.py
tests/basic_test.py
tests/common.py
tests/highlight_test.py
tests/multi_db_test.py
tests/multi_design_test.py
tests/order_test.py
tests/unicode_test.py