Metadata-Version: 1.0
Name: hypercouch
Version: 0.3
Summary: Full Text Indexing for CouchDB
Home-page: http://github.com/davisp/hypercouch
Author: Paul J. Davis
Author-email: paul.joseph.davis@gmail.com
License: MIT
Platform: UNKNOWN
Classifier: Development Status :: 3 - Alpha
Classifier: Intended Audience :: Developers
Classifier: License :: OSI Approved :: MIT License
Classifier: Operating System :: OS Independent
Classifier: Programming Language :: Python
Classifier: Topic :: Database :: Front-Ends
Classifier: Topic :: Software Development :: Libraries :: Python Modules
Classifier: Topic :: Internet :: WWW/HTTP :: Indexing/Search
